<DOMSymbolItem xmlns:xsi="http://www.w3.org/2001/XMLSchema-instance" xmlns="http://ns.adobe.com/xfl/2008/" name="Scenes/TC_TScene__Scene11" itemID="5ba00e1d-000018f8" linkageExportForAS="true" linkageClassName="TC_TScene__Scene11" lastModified="1537219422">
  <persistentData>
    <PD n="CreateJSToolkit_timelinedata" v="version&#xA;0.1&#xA;loop&#xA;true"/>
  </persistentData>
  <timeline>
    <DOMTimeline name="TC_TScene__Scene11">
      <layers>
        <DOMLayer name="Layer_2" color="#9933CC" current="true" isSelected="true">
          <frames>
            <DOMFrame index="0" keyMode="9728">
              <elements>
                <DOMSymbolInstance libraryItemName="_HTMLControls/TC_THtmlText__Text1" name="Stitle">
                  <matrix>
                    <Matrix a="15.6493835449219" d="4.95903015136719" tx="181.45" ty="294.9"/>
                  </matrix>
                  <transformationPoint>
                    <Point x="49.35" y="50.25"/>
                  </transformationPoint>
                </DOMSymbolInstance>
              </elements>
            </DOMFrame>
          </frames>
        </DOMLayer>
        <DOMLayer name="SceneRegion" color="#00FFFF" outline="true" useOutlineView="true" autoNamed="false">
          <frames>
            <DOMFrame index="0" keyMode="9728">
              <elements>
                <DOMSymbolInstance libraryItemName="_Tutor Global Assets_/TC_TVirtual__SceneRgn">
                  <transformationPoint>
                    <Point x="960" y="600"/>
                  </transformationPoint>
                </DOMSymbolInstance>
              </elements>
            </DOMFrame>
          </frames>
        </DOMLayer>
      </layers>
    </DOMTimeline>
  </timeline>
</DOMSymbolItem>